daacla/__init__.py
daacla/convert.py
tests/__init__.py
tests/test_decorator.py
daacla-0.0.8.dist-info/LICENSE
daacla-0.0.8.dist-info/METADATA
daacla-0.0.8.dist-info/WHEEL
daacla-0.0.8.dist-info/top_level.txt
daacla-0.0.8.dist-info/RECORD
