Metadata-Version: 2.1
Name: daacla
Version: 0.0.8
Summary: Python module to management `dataclass` objects using SQLite
Home-page: https://github.com/anekos/daacla
Author: anekos
Author-email: pypi@snca.net
License: UNKNOWN
Platform: UNKNOWN
Classifier: Programming Language :: Python :: 3.7
Classifier: License :: OSI Approved :: MIT License
Classifier: Operating System :: OS Independent
License-File: LICENSE
Requires-Dist: appdirs
Requires-Dist: pytest
Requires-Dist: python-dateutil
